{
  "swagger": "2.0",
  "info": {
    "version": "1.0",
    "title": "todo-api"
  },
  "schemes": [
    "https"
  ],
  "consumes": [
    "application/json"
  ],
  "produces": [
    "application/json"
  ],
  "paths": {
    "/get": {
      "get": {
        "operationId": "Get Item",
        "x-openwhisk": {
          "action": "todo-get",
          "package": "default"
        },
        "responses": {
          "200": {
            "description": "A successful invocation response"
          }
        }
      }
    },
    "/lst": {
      "get": {
        "operationId": "List Items",
        "x-openwhisk": {
          "action": "todo-lst",
          "package": "default"
        },
        "responses": {
          "200": {
            "description": "A successful invocation response"
          }
        }
      }
    },
    "/del": {
      "post": {
        "operationId": "Delete Item",
        "x-openwhisk": {
          "action": "todo-del",
          "package": "default"
        },
        "responses": {
          "200": {
            "description": "A successful invocation response"
          }
        },
        "parameters": [
          {
            "name": "body",
            "in": "body",
            "description": "Request body",
            "required": false,
            "schema": {
              "type": "object"
            }
          }
        ]
      }
    },
    "/put": {
      "post": {
        "operationId": "Put Item",
        "x-openwhisk": {
          "action": "todo-put",
          "package": "default"
        },
        "responses": {
          "200": {
            "description": "A successful invocation response"
          }
        },
        "parameters": [
          {
            "name": "body",
            "in": "body",
            "description": "Request body",
            "required": false,
            "schema": {
              "type": "object"
            }
          }
        ]
      }
    },
    "/done": {
      "post": {
        "operationId": "Mark as Done",
        "x-openwhisk": {
          "action": "todo-done",
          "package": "default"
        },
        "responses": {
          "200": {
            "description": "A successful invocation response"
          }
        },
        "parameters": [
          {
            "name": "body",
            "in": "body",
            "description": "Request body",
            "required": false,
            "schema": {
              "type": "object"
            }
          }
        ]
      }
    }
  },
  "basePath": "/api",
  "securityDefinitions": {},
  "security": [
    {}
  ]
}